QualiCSCLI.py
Table.py
QualiCSCLI-0.4.dist-info/DESCRIPTION.rst
QualiCSCLI-0.4.dist-info/entry_points.txt
QualiCSCLI-0.4.dist-info/METADATA
QualiCSCLI-0.4.dist-info/metadata.json
QualiCSCLI-0.4.dist-info/RECORD
QualiCSCLI-0.4.dist-info/top_level.txt
QualiCSCLI-0.4.dist-info/WHEEL
